mapyreduce/__init__.py
mapyreduce/mapyreduce.py
mapyreduce-0.2.0.dist-info/METADATA
mapyreduce-0.2.0.dist-info/WHEEL
mapyreduce-0.2.0.dist-info/RECORD
