Metadata-Version: 2.1
Name: mapyreduce
Version: 0.2.0
Summary: Lightweight and extensible library to execute MapReduce-like jobs in Python
Home-page: https://github.com/Samuele95/mapyreduce
License: MIT
Author: Samuele95
Author-email: strsml095@gmail.com
Requires-Python: >=3.12,<4.0
Classifier: License :: OSI Approved :: MIT License
Classifier: Programming Language :: Python :: 3
Classifier: Programming Language :: Python :: 3.12
Classifier: Programming Language :: Python :: 3.13
Requires-Dist: multiprocess (>=0.70.17,<0.71.0)
Requires-Dist: pytest (>=8.3.4,<9.0.0)
Project-URL: Repository, https://github.com/Samuele95/mapyreduce
